futureframe/__init__.py
futureframe/config.py
futureframe/data/__init__.py
futureframe/data/download.py
futureframe/data/features.py
futureframe/data/tabular_datasets.py
futureframe/encoding/__init__.py
futureframe/encoding/base.py
futureframe/encoding/fastt.py
futureframe/encoding/llm.py
futureframe/encoding/num.py
futureframe/evaluation.py
futureframe/finetuning.py
futureframe/inference.py
futureframe/logger.py
futureframe/models/__init__.py
futureframe/models/base.py
futureframe/models/cm2.py
futureframe/models/tabtext.py
futureframe/optim.py
futureframe/tasks.py
futureframe/types.py
futureframe/utils.py
futureframe-0.2.5.dist-info/LICENSE
futureframe-0.2.5.dist-info/METADATA
futureframe-0.2.5.dist-info/WHEEL
futureframe-0.2.5.dist-info/RECORD
