Metadata-Version: 2.1
Name: futureframe
Version: 0.2.5
Summary: Accelerate your data science workflow from months to days with foundation models for tabular data.
Home-page: https://futureframe.ai
Keywords: data science,foundation models,tabular data
Author: Future Frame
Maintainer: Eduardo Dadalto
Maintainer-email: eduardo@futureframe.ai
Requires-Python: >=3.10,<4.0
Classifier: Programming Language :: Python :: 3
Classifier: Programming Language :: Python :: 3.10
Classifier: Programming Language :: Python :: 3.11
Classifier: Programming Language :: Python :: 3.12
Requires-Dist: catboost (>=1.2.5,<2.0.0)
Requires-Dist: fire (>=0.6.0,<0.7.0)
Requires-Dist: numpy (>=1.17,<2.0)
Requires-Dist: openml (>=0.14.2,<0.15.0)
Requires-Dist: pandas (>=2.2.2,<3.0.0)
Requires-Dist: pyarrow (>=16.1.0,<17.0.0)
Requires-Dist: pydantic (>=2.7.2,<3.0.0)
Requires-Dist: rich (>=13.7.1,<14.0.0)
Requires-Dist: scikit-learn (>=1.4.2,<2.0.0)
Requires-Dist: sentence-transformers (>=3.0.1,<4.0.0)
Requires-Dist: torch (>=2,<3)
Requires-Dist: torchmetrics (>=1.4.0.post0,<2.0.0)
Requires-Dist: transformers (>=4.41.0,<5.0.0)
Requires-Dist: xgboost (>=2.1.0,<3.0.0)
Project-URL: Documentation, https://futureframe.ai/docs
Project-URL: Repository, https://github.com/futureframeai/futureframe
